pycnet/__init__.py
pycnet/access_log.py
pycnet/calendar.py
pycnet/query.py
pycnet/staff.py
pycnet/student.py
pycnet/subject.py
pycnet-1.0.6.dist-info/LICENSE
pycnet-1.0.6.dist-info/METADATA
pycnet-1.0.6.dist-info/WHEEL
pycnet-1.0.6.dist-info/top_level.txt
pycnet-1.0.6.dist-info/RECORD
