Metadata-Version: 2.1
Name: pycnet
Version: 1.0.6
Summary: A personal package.
Home-page: https://github.com
Author: d_mok
Author-email: unknown@gmail.com
License: MIT
Platform: UNKNOWN
Classifier: Programming Language :: Python :: 3
Classifier: License :: OSI Approved :: MIT License
Classifier: Operating System :: OS Independent
Requires-Dist: pandas
Requires-Dist: pandas-light
Requires-Dist: pandas-flavor
